datpack_update/__init__.py
datpack_update/__main__.py
datpack_update/main.py
datpack_update-1.1.1.dist-info/LICENSE
datpack_update-1.1.1.dist-info/METADATA
datpack_update-1.1.1.dist-info/WHEEL
datpack_update-1.1.1.dist-info/entry_points.txt
datpack_update-1.1.1.dist-info/RECORD
