Metadata-Version: 2.1
Name: datpack-update
Version: 1.1.1
Summary: Update No-Intro DAT files
Home-page: https://github.com/agsimmons/datpack-update
License: GPL-3.0-only
Author: Andrew Simmons
Author-email: agsimmons0@gmail.com
Requires-Python: >=3.8.1,<4.0.0
Classifier: License :: OSI Approved :: GNU General Public License v3 (GPLv3)
Classifier: Programming Language :: Python :: 3
Classifier: Programming Language :: Python :: 3.9
Classifier: Programming Language :: Python :: 3.10
Classifier: Programming Language :: Python :: 3.11
Project-URL: Repository, https://github.com/agsimmons/datpack-update
